config_tools.py
query.py
setup.py
prom_metric_tools-0.0.2.dist-info/LICENSE
prom_metric_tools-0.0.2.dist-info/METADATA
prom_metric_tools-0.0.2.dist-info/WHEEL
prom_metric_tools-0.0.2.dist-info/top_level.txt
prom_metric_tools-0.0.2.dist-info/RECORD
